README.md
setup.py
lineusmusic/__init__.py
lineusmusic/keyboard.py
lineusmusic.egg-info/PKG-INFO
lineusmusic.egg-info/SOURCES.txt
lineusmusic.egg-info/dependency_links.txt
lineusmusic.egg-info/requires.txt
lineusmusic.egg-info/top_level.txt