Metadata-Version: 1.0
Name: lineusmusic
Version: 1.0.0
Summary: The Python module for Line-us Music
Home-page: https://github.com/Line-us/LineUsMusic
Author: Robert Poll
Author-email: rob@line-us.com
License: MIT
Platform: UNKNOWN
